{"version": "1", "message": "ERROR: Hidden Testcases server unreachable.", "problem_id": "ads2_m10_a1_1", "user_id": "vipulcharkravarthy", "score": {"sample": {"0": {"execution_time": 1.0374279022216797, "passed": true}, "1": {"execution_time": 0.9351813793182373, "passed": true}, "2": {"execution_time": 0.8626971244812012, "passed": true}, "3": {"execution_time": 0.3420379161834717, "passed": true}, "4": {"execution_time": 0.8785979747772217, "passed": true}, "5": {"execution_time": 1.3461785316467285, "passed": true}, "6": {"execution_time": 2.933978319168091, "passed": true}, "7": {"execution_time": 0.47043728828430176, "passed": true}, "8": {"execution_time": 2.625653028488159, "passed": true}}}, "check_style_score": "0/1"}